syxhhhq/__init__.py
syxhhhq/lymasterdd.py
syxhhhq/syx1.py
syxhhhq/syx2.py
syxhhhq-0.0.1.dist-info/LICENSE.txt
syxhhhq-0.0.1.dist-info/METADATA
syxhhhq-0.0.1.dist-info/WHEEL
syxhhhq-0.0.1.dist-info/top_level.txt
syxhhhq-0.0.1.dist-info/RECORD
